infinit/__init__.py
infinit/cli/__init__.py
infinit/cli/__main__.py
infinit/cli/create.py
infinit/cli/template.py
infinit/core/__init__.py
infinit/core/exceptions.py
infinit/core/scaffold.py
infinit/core/templates.py
infinit-0.1.0.dist-info/METADATA
infinit-0.1.0.dist-info/WHEEL
infinit-0.1.0.dist-info/entry_points.txt
infinit-0.1.0.dist-info/top_level.txt
infinit-0.1.0.dist-info/RECORD
