Metadata-Version: 2.4
Name: infinit
Version: 0.1.0
Summary: Minimal project scaffolder for hackers
Author-email: hoverdd <lenyamenshov@gmail.com>
License: BSD-2-Clause
Keywords: scaffolding,template,productivity
Classifier: Development Status :: 4 - Beta
Classifier: Environment :: Console
Classifier: Intended Audience :: Developers
Requires-Python: >=3.9
Requires-Dist: click>=8.1.3
Requires-Dist: pyyaml>=6.0.2
Provides-Extra: dev
Requires-Dist: pytest>=8.0; extra == "dev"
Requires-Dist: pytest-cov; extra == "dev"
Requires-Dist: black; extra == "dev"
Requires-Dist: mypy; extra == "dev"
